{
    "isFavorite": false,
    "items": [
        {
            "coin": "WALA",
            "pool_ssl": false,
            "dpool_ssl": false,
            "miner": "lolminer",
            "miner_config": {
                "url": "127.0.0.1:5555",
                "algo": "WALAHASH",
                "worker": "%WORKER_NAME%",
                "user_config": "--disable-cpu"
            },
            "pool_geo": []
        },
        {
            "coin": "WALA",
            "pool_ssl": false,
            "dpool_ssl": false,
            "miner": "custom",
            "miner_alt": "wala_bridge",
            "miner_config": {
                "url": "YOUR_WAGLAYLAD_NODE_IP_HERE:12110",
                "miner": "wala_bridge",
                "template": "doesnt.matter",
                "install_url": "https://github.com/waglayla/waglayla-stratum-bridge/releases/download/v1.1.2/wala_bridge-1.1.2_hive.tar.gz"
            },
            "pool_geo": []
        }
    ]
}
